example_package_coolport/__init__.py
example_package_coolport/example.py
example_package_coolport-0.0.10.dist-info/WHEEL
example_package_coolport-0.0.10.dist-info/METADATA
example_package_coolport-0.0.10.dist-info/RECORD
