Metadata-Version: 2.4
Name: example_package_coolport
Version: 0.0.10
Summary: pypi, git tags, workflow, cicd practice package
Author: Aidan Alcayde
Author-email: Aidan Alcayde <aidanalcayde@gmail.com>
License-Expression: MIT
Classifier: Programming Language :: Python :: 3
Classifier: Operating System :: OS Independent
Requires-Python: >=3.9
Project-URL: Homepage, https://github.com/pypa/sampleproject
Project-URL: Issues, https://github.com/pypa/sampleproject/issues
